# pydisasm version 5.0.8
# Python bytecode 3.9 ()
# Disassembled from Python 3.9.2 (default, Feb 28 2021, 17:03:44) 
# [GCC 10.2.1 20210110]
# Timestamp in code: 0 (1969-12-31 19:00:00)

# Method Name:       
# Filename:          
# Argument count:    1
# Position-only argument count: 0
# Keyword-only arguments: 0
# Number of locals:  7
# Stack size:        38
# Flags:             0x00000043 (NOFREE | NEWLOCALS | OPTIMIZED)
# First Line:        0
# Constants:
#    0: None
#    1: 0
#    2: True
#    3: -1
#    4: (1, 0, 0, 1, 0, -1, 1, -1, -1, 0, 0, -1, 0, 0, -1, 1)
#    5: (1, 1, 1, 0, -1, 0, -1, -1, 1, 1, -1, 1, 0, 0, 0, -1)
#    6: (0, 0, 1, 0, -1, 1, -1, -1, 0, 0, 1, 1, -1, -1, 0, -1)
#    7: (0, 1, 0, 1, -1, -1, 1, 0, -1, 0, 1, 1, 1, -1, -1, 0)
#    8: (0, 0, 0, 0, -1, 1, 0, -1, -1, -1, 1, 1, -1, -1, 0, 0)
#    9: (0, 0, 1, 1, 0, 0, 1, 0, 0, 0, 1, 1, -1, 1, -1, 0)
#   10: (-1, 0, -1, 1, 1, 1, -1, 0, 1, -1, -1, 0, -1, 0, 1, 1)
#   11: (0, 1, -1, 1, 1, 1, 1, 1, -1, 1, -1, 1, 0, 1, -1, 0)
#   12: (0, 0, 1, 1, -1, 1, -1, 0, 1, 1, -1, 1, 1, 1, -1, -1)
#   13: (-1, 1, 0, -1, 1, 1, 1, 0, 1, -1, 0, 0, -1, 1, 0, -1)
#   14: (0, 0, -1, 1, -1, 0, 0, 0, -1, -1, -1, 1, -1, 1, 1, -1)
#   15: (0, 0, -1, 1, -1, 1, -1, -1, 1, -1, -1, -1, 0, 1, 0, 0)
#   16: (0, -1, 0, 0, -1, -1, -1, -1, -1, 0, -1, 0, -1, 0, 0, -1)
#   17: (0, -1, 0, -1, 1, 1, 0, 1, -1, 1, 1, 0, 0, 1, -1, -1)
#   18: (0, 0, 1, -1, 0, 0, 0, 0, 0, 1, 1, 0, 0, 1, 0, -1)
#   19: (1, 1, 1, 1, -1, 1, 1, 0, -1, 0, 0, -1, 1, 0, -1, 1)
#   20: (0, -1, 1, -1, 1, 0, 1, -1, -1, 0, -1, -1, 0, 0, -1, -1)
#   21: (0, -1, -1, -1, 1, -1, 1, 1, -1, -1, 0, 0, 0, -1, -1, 0)
#   22: (0, 0, -1, -1, -1, -1, -1, 1, 1, 0, -1, -1, 0, -1, -1, 1)
#   23: 16
#   24: 1
#   25: False
# Names:
#    0: random
#    1: zip
#    2: seed
#    3: range
#    4: append
#    5: randint
# Varnames:
#	f, random, _____, ___, ____, _, __
# Positional arguments:
#	f
# Local variables:
#    1: random
#    2: _____
#    3: ___
#    4: ____
#    5: _
#    6: __
  0:           0 LOAD_CONST           (0)
               2 LOAD_CONST           (None)
               4 IMPORT_NAME          (random)
               6 STORE_FAST           (random)  	random =random(0)
               8 LOAD_CONST           (True)
              10 STORE_FAST           (_____)		#_____ =True
              12 LOAD_GLOBAL          (zip)    		#zip()
              14 LOAD_FAST            (f)		#f
              16 LOAD_CONST           (None)
              18 LOAD_CONST           (None)
              20 LOAD_CONST           (-1)		
              22 BUILD_SLICE          3			#3 var --> slice (None, None, -1)
              24 BINARY_SUBSCR				#f[::-1]
              26 BUILD_LIST           0			#arr=[]
              28 LOAD_CONST           ((1, 0, 0, 1, 0, -1, 1, -1, -1, 0, 0, -1, 0, 0, -1, 1))
              30 LIST_EXTEND          1			#arr.append()
              32 BUILD_LIST           0
              34 LOAD_CONST           ((1, 1, 1, 0, -1, 0, -1, -1, 1, 1, -1, 1, 0, 0, 0, -1))
              36 LIST_EXTEND          1			#arr.append()
              38 BUILD_LIST           0
              40 LOAD_CONST           ((0, 0, 1, 0, -1, 1, -1, -1, 0, 0, 1, 1, -1, -1, 0, -1))
              42 LIST_EXTEND          1			#arr.append()
              44 BUILD_LIST           0
              46 LOAD_CONST           ((0, 1, 0, 1, -1, -1, 1, 0, -1, 0, 1, 1, 1, -1, -1, 0))
              48 LIST_EXTEND          1			#arr.append()
              50 BUILD_LIST           0
              52 LOAD_CONST           ((0, 0, 0, 0, -1, 1, 0, -1, -1, -1, 1, 1, -1, -1, 0, 0))
              54 LIST_EXTEND          1			#arr.append()
              56 BUILD_LIST           0
              58 LOAD_CONST           ((0, 0, 1, 1, 0, 0, 1, 0, 0, 0, 1, 1, -1, 1, -1, 0))
              60 LIST_EXTEND          1			#arr.append()
              62 BUILD_LIST           0
              64 LOAD_CONST           ((0, 1, 0, 1, -1, -1, 1, 0, -1, 0, 1, 1, 1, -1, -1, 0))
              66 LIST_EXTEND          1			#arr.append()
              68 BUILD_LIST           0
              70 LOAD_CONST           ((-1, 0, -1, 1, 1, 1, -1, 0, 1, -1, -1, 0, -1, 0, 1, 1))
              72 LIST_EXTEND          1			#arr.append()
              74 BUILD_LIST           0
              76 LOAD_CONST           ((0, 1, -1, 1, 1, 1, 1, 1, -1, 1, -1, 1, 0, 1, -1, 0))
              78 LIST_EXTEND          1
              80 BUILD_LIST           0
              82 LOAD_CONST           ((0, 0, 0, 0, -1, 1, 0, -1, -1, -1, 1, 1, -1, -1, 0, 0))
              84 LIST_EXTEND          1
              86 BUILD_LIST           0
              88 LOAD_CONST           ((0, 0, 1, 1, -1, 1, -1, 0, 1, 1, -1, 1, 1, 1, -1, -1))
              90 LIST_EXTEND          1
              92 BUILD_LIST           0
              94 LOAD_CONST           ((0, 0, 1, 1, 0, 0, 1, 0, 0, 0, 1, 1, -1, 1, -1, 0))
              96 LIST_EXTEND          1
              98 BUILD_LIST           0
             100 LOAD_CONST           ((-1, 1, 0, -1, 1, 1, 1, 0, 1, -1, 0, 0, -1, 1, 0, -1))
             102 LIST_EXTEND          1
             104 BUILD_LIST           0
             106 LOAD_CONST           ((0, 0, 1, 1, 0, 0, 1, 0, 0, 0, 1, 1, -1, 1, -1, 0))
             108 LIST_EXTEND          1
             110 BUILD_LIST           0
             112 LOAD_CONST           ((0, 0, 0, 0, -1, 1, 0, -1, -1, -1, 1, 1, -1, -1, 0, 0))
             114 LIST_EXTEND          1
             116 BUILD_LIST           0
             118 LOAD_CONST           ((0, 0, -1, 1, -1, 0, 0, 0, -1, -1, -1, 1, -1, 1, 1, -1))
             120 LIST_EXTEND          1
             122 BUILD_LIST           0
             124 LOAD_CONST           ((0, 0, 1, 1, 0, 0, 1, 0, 0, 0, 1, 1, -1, 1, -1, 0))
             126 LIST_EXTEND          1
             128 BUILD_LIST           0
             130 LOAD_CONST           ((0, 0, 1, 0, -1, 1, -1, -1, 0, 0, 1, 1, -1, -1, 0, -1))
             132 LIST_EXTEND          1
             134 BUILD_LIST           0
             136 LOAD_CONST           ((0, 0, -1, 1, -1, 1, -1, -1, 1, -1, -1, -1, 0, 1, 0, 0))
             138 LIST_EXTEND          1
             140 BUILD_LIST           0
             142 LOAD_CONST           ((0, 0, -1, 1, -1, 1, -1, -1, 1, -1, -1, -1, 0, 1, 0, 0))
             144 LIST_EXTEND          1
             146 BUILD_LIST           0
             148 LOAD_CONST           ((0, -1, 0, 0, -1, -1, -1, -1, -1, 0, -1, 0, -1, 0, 0, -1))
             150 LIST_EXTEND          1
             152 BUILD_LIST           0
             154 LOAD_CONST           ((0, -1, 0, -1, 1, 1, 0, 1, -1, 1, 1, 0, 0, 1, -1, -1))
             156 LIST_EXTEND          1
             158 BUILD_LIST           0
             160 LOAD_CONST           ((0, 0, 1, 1, 0, 0, 1, 0, 0, 0, 1, 1, -1, 1, -1, 0))
             162 LIST_EXTEND          1
             164 BUILD_LIST           0
             166 LOAD_CONST           ((0, 0, 1, -1, 0, 0, 0, 0, 0, 1, 1, 0, 0, 1, 0, -1))
             168 LIST_EXTEND          1
             170 BUILD_LIST           0
             172 LOAD_CONST           ((0, 0, 0, 0, -1, 1, 0, -1, -1, -1, 1, 1, -1, -1, 0, 0))
             174 LIST_EXTEND          1
             176 BUILD_LIST           0
             178 LOAD_CONST           ((0, 0, -1, 1, -1, 0, 0, 0, -1, -1, -1, 1, -1, 1, 1, -1))
             180 LIST_EXTEND          1
             182 BUILD_LIST           0
             184 LOAD_CONST           ((1, 1, 1, 0, -1, 0, -1, -1, 1, 1, -1, 1, 0, 0, 0, -1))
             186 LIST_EXTEND          1
             188 BUILD_LIST           0
             190 LOAD_CONST           ((0, 0, 1, 0, -1, 1, -1, -1, 0, 0, 1, 1, -1, -1, 0, -1))
             192 LIST_EXTEND          1
             194 BUILD_LIST           0
             196 LOAD_CONST           ((0, 1, 0, 1, -1, -1, 1, 0, -1, 0, 1, 1, 1, -1, -1, 0))
             198 LIST_EXTEND          1
             200 BUILD_LIST           0
             202 LOAD_CONST           ((0, 0, 0, 0, -1, 1, 0, -1, -1, -1, 1, 1, -1, -1, 0, 0))
             204 LIST_EXTEND          1
             206 BUILD_LIST           0
             208 LOAD_CONST           ((1, 1, 1, 1, -1, 1, 1, 0, -1, 0, 0, -1, 1, 0, -1, 1))
             210 LIST_EXTEND          1
             212 BUILD_LIST           0
             214 LOAD_CONST           ((0, -1, 1, -1, 1, 0, 1, -1, -1, 0, -1, -1, 0, 0, -1, -1))
             216 LIST_EXTEND          1
             218 BUILD_LIST           0
             220 LOAD_CONST           ((1, 1, 1, 0, -1, 0, -1, -1, 1, 1, -1, 1, 0, 0, 0, -1))
             222 LIST_EXTEND          1
             224 BUILD_LIST           0
             226 LOAD_CONST           ((0, -1, -1, -1, 1, -1, 1, 1, -1, -1, 0, 0, 0, -1, -1, 0))
             228 LIST_EXTEND          1
             230 BUILD_LIST           0
             232 LOAD_CONST           ((0, 0, -1, -1, -1, -1, -1, 1, 1, 0, -1, -1, 0, -1, -1, 1))
             234 LIST_EXTEND          1
             236 BUILD_LIST           35		
             238 CALL_FUNCTION        2			#zip(f[::-1], arr)
             240 GET_ITER
         >>  242 FOR_ITER             (to 312)		# for i in zip(f[::-1], arr):
             244 UNPACK_SEQUENCE      2
             246 STORE_FAST           (___)		#___= i[0]
             248 STORE_FAST           (____)		#____ =i[1]
             250 LOAD_FAST            (random)
             252 LOAD_METHOD          (seed)		#random.seed()
             254 LOAD_FAST            (___)
             256 CALL_METHOD          1			#random.seed(___)
             258 POP_TOP
             260 BUILD_LIST           0
             262 STORE_FAST           (_)		#_ =[]
             264 LOAD_GLOBAL          (range)
             266 LOAD_CONST           (16)
             268 CALL_FUNCTION        1			#range(16)
             270 GET_ITER
         >>  272 FOR_ITER             (to 298)
             274 STORE_FAST           (__)
             276 LOAD_FAST            (_)
             278 LOAD_METHOD          (append)
             280 LOAD_FAST            (random)
             282 LOAD_METHOD          (randint)
             284 LOAD_CONST           (-1)
             286 LOAD_CONST           (1)
             288 CALL_METHOD          2
             290 CALL_METHOD          1
             292 POP_TOP
             294 EXTENDED_ARG         (256)
             296 JUMP_ABSOLUTE        (to 272)
         >>  298 LOAD_FAST            (_)
             300 LOAD_FAST            (____)
             302 COMPARE_OP           (!=)
             304 POP_JUMP_IF_FALSE    (to 242)
             306 LOAD_CONST           (False)
             308 STORE_FAST           (_____)
             310 JUMP_ABSOLUTE        (to 242)
         >>  312 LOAD_FAST            (_____)
             314 RETURN_VALUE

